LICENSE
MANIFEST.in
README.md
setup.cfg
setup.py
textgetter/__init__.py
textgetter/getcsv.py
textgetter/getdocx.py
textgetter/getexcel.py
textgetter/gettxt.py
textgetter.egg-info/PKG-INFO
textgetter.egg-info/SOURCES.txt
textgetter.egg-info/dependency_links.txt
textgetter.egg-info/requires.txt
textgetter.egg-info/top_level.txt
textgetter/poppler/bin/AUTHORS
textgetter/poppler/bin/BINARIES
textgetter/poppler/bin/COPYING
textgetter/poppler/bin/COPYING3
textgetter/poppler/bin/README
textgetter/poppler/bin/README-XPDF
textgetter/poppler/bin/freetype6.dll
textgetter/poppler/bin/jpeg62.dll
textgetter/poppler/bin/libcairo-2.dll
textgetter/poppler/bin/libexpat-1.dll
textgetter/poppler/bin/libfontconfig-1.dll
textgetter/poppler/bin/libgcc_s_dw2-1.dll
textgetter/poppler/bin/libpixman-1-0.dll
textgetter/poppler/bin/libpng16-16.dll
textgetter/poppler/bin/libpoppler-79.dll
textgetter/poppler/bin/libpoppler-cpp-0.dll
textgetter/poppler/bin/libstdc++-6.dll
textgetter/poppler/bin/libtiff3.dll
textgetter/poppler/bin/pdfdetach.exe
textgetter/poppler/bin/pdffonts.exe
textgetter/poppler/bin/pdfimages.exe
textgetter/poppler/bin/pdfinfo.exe
textgetter/poppler/bin/pdfseparate.exe
textgetter/poppler/bin/pdftocairo.exe
textgetter/poppler/bin/pdftohtml.exe
textgetter/poppler/bin/pdftoppm.exe
textgetter/poppler/bin/pdftops.exe
textgetter/poppler/bin/pdftotext.exe
textgetter/poppler/bin/pdfunite.exe
textgetter/poppler/bin/zlib1.dll
textgetter/poppler/include/poppler/cpp/poppler-document.h
textgetter/poppler/include/poppler/cpp/poppler-embedded-file.h
textgetter/poppler/include/poppler/cpp/poppler-font.h
textgetter/poppler/include/poppler/cpp/poppler-global.h
textgetter/poppler/include/poppler/cpp/poppler-image.h
textgetter/poppler/include/poppler/cpp/poppler-page-renderer.h
textgetter/poppler/include/poppler/cpp/poppler-page-transition.h
textgetter/poppler/include/poppler/cpp/poppler-page.h
textgetter/poppler/include/poppler/cpp/poppler-rectangle.h
textgetter/poppler/include/poppler/cpp/poppler-toc.h
textgetter/poppler/include/poppler/cpp/poppler-version.h
textgetter/poppler/lib/libpoppler-cpp.dll.a
textgetter/poppler/lib/libpoppler.dll.a
