Metadata-Version: 2.1
Name: textgetter
Version: 0.0.1
Summary: A python package for extracting text from PDF/TIF/JPG/PNG files
Home-page: https://github.com/scionoftech/textgetter
Author: Sai Kumar Yava
Author-email: saikumar.geek@gmail.com
License: MIT
Download-URL: https://github.com/scionoftech/textgetter/releases/tag/textgetter_stable_v0.0.1
Keywords: pdf,tif,tiff,image,text
Platform: UNKNOWN
Classifier: Development Status :: 5 - Production/Stable
Classifier: Programming Language :: Python
Classifier: Programming Language :: Python :: 3
Classifier: Programming Language :: Python :: 3.5
Classifier: Programming Language :: Python :: 3.6
Classifier: Programming Language :: Python :: 3.7
Classifier: Programming Language :: Python :: Implementation :: CPython
Classifier: Programming Language :: Python :: Implementation :: PyPy
Classifier: License :: OSI Approved :: MIT License
